proteovae/__init__.py
proteovae/disentanglement/__init__.py
proteovae/disentanglement/metrics.py
proteovae/models/__init__.py
proteovae/models/base.py
proteovae/models/models.py
proteovae/models/utils.py
proteovae/trainers/Trainers.py
proteovae/trainers/__init__.py
proteovae-0.0.1.dist-info/LICENSE
proteovae-0.0.1.dist-info/METADATA
proteovae-0.0.1.dist-info/WHEEL
proteovae-0.0.1.dist-info/top_level.txt
proteovae-0.0.1.dist-info/RECORD
