Metadata-Version: 2.1
Name: proteovae
Version: 0.0.1
Summary: package for implementing guided variational autoencoders
Home-page: https://github.com/nnethercott/proteovae
Author: Nate Nethercott
Author-email: natenethercott@gmail.com
License: MIT
Classifier: Development Status :: 3 - Alpha
Classifier: Programming Language :: Python :: 3
Classifier: Operating System :: Unix
License-File: LICENSE
Requires-Dist: numpy (==1.22.4)
Requires-Dist: pydantic (==1.10.7)
Requires-Dist: scikit-learn (==1.2.2)
Requires-Dist: torch (==2.0.0)
Requires-Dist: tqdm (==4.65.0)
Provides-Extra: tutorial
Requires-Dist: torchvision (==0.15.1) ; extra == 'tutorial'
Requires-Dist: jupyter ; extra == 'tutorial'
Requires-Dist: matplotlib (==3.7.1) ; extra == 'tutorial'
